<?xml version="1.0" encoding="UTF-8"?> 
<list xmlns:xsi="http://www.w3.org/2001/XMLSchema-instance" xsi:noNamespaceSchemaLocation="../../xsd/optionsData.xsd">
	<option id="31900" name="helios_opt">
		<!-- Passive: Pull/Petrification Resistance + 6%. -->
		<passive_skill id="13755" level="4" />
	</option>
	<option id="31901" name="helios_opt">
		<!-- P. Def. + 22 -->
	</option>
	<option id="31902" name="helios_opt">
		<!-- P. Def. + 26 -->
	</option>
	<option id="31903" name="helios_opt">
		<!-- P. Def. + 34 -->
	</option>
	<option id="31904" name="helios_opt">
		<!-- P. Def. + 42 -->
	</option>
	<option id="31905" name="helios_opt">
		<!-- P. Def. + 50 -->
	</option>
	<option id="31906" name="helios_opt">
		<!-- P. Def. + 61 -->
	</option>
	<option id="31907" name="helios_opt">
		<!-- P. Def. + 71 -->
	</option>
	<option id="31908" name="helios_opt">
		<!-- P. Def. + 81 -->
	</option>
	<option id="31909" name="helios_opt">
		<!-- P. Def. + 101 -->
	</option>
	<option id="31910" name="helios_opt">
		<!-- P. Def. + 203 -->
	</option>
	<option id="31911" name="helios_opt">
		<!-- M. Def. + 22 -->
	</option>
	<option id="31912" name="helios_opt">
		<!-- M. Def. + 26 -->
	</option>
	<option id="31913" name="helios_opt">
		<!-- M. Def. + 34 -->
	</option>
	<option id="31914" name="helios_opt">
		<!-- M. Def. + 42 -->
	</option>
	<option id="31915" name="helios_opt">
		<!-- M. Def. + 50 -->
	</option>
	<option id="31916" name="helios_opt">
		<!-- M. Def. + 61 -->
	</option>
	<option id="31917" name="helios_opt">
		<!-- M. Def. + 71 -->
	</option>
	<option id="31918" name="helios_opt">
		<!-- M. Def. + 81 -->
	</option>
	<option id="31919" name="helios_opt">
		<!-- M. Def. + 101 -->
	</option>
	<option id="31920" name="helios_opt">
		<!-- M. Def. + 203 -->
	</option>
	<option id="31921" name="helios_opt">
		<!-- P. Evasion + 1 -->
	</option>
	<option id="31922" name="helios_opt">
		<!-- P. Evasion + 2 -->
	</option>
	<option id="31923" name="helios_opt">
		<!-- P. Evasion + 3 -->
	</option>
	<option id="31924" name="helios_opt">
		<!-- Passive: M. Evasion + 1. -->
		<passive_skill id="13760" level="6" />
	</option>
	<option id="31925" name="helios_opt">
		<!-- Passive: M. Evasion + 2. -->
		<passive_skill id="13760" level="7" />
	</option>
	<option id="31926" name="helios_opt">
		<!-- Passive: M. Evasion + 3. -->
		<passive_skill id="13760" level="8" />
	</option>
	<option id="31927" name="helios_opt">
		<!-- Speed + 3 -->
	</option>
	<option id="31928" name="helios_opt">
		<!-- Speed + 4 -->
	</option>
	<option id="31929" name="helios_opt">
		<!-- Speed + 5 -->
	</option>
	<option id="31930" name="helios_opt">
		<!-- Speed + 10 -->
	</option>
	<option id="31931" name="helios_opt">
		<!-- HP Recovery Rate + 1 -->
	</option>
	<option id="31932" name="helios_opt">
		<!-- HP Recovery Rate + 2 -->
	</option>
	<option id="31933" name="helios_opt">
		<!-- HP Recovery Rate + 3 -->
	</option>
	<option id="31934" name="helios_opt">
		<!-- HP Recovery Rate + 5 -->
	</option>
	<option id="31935" name="helios_opt">
		<!-- MP Recovery Rate + 1 -->
	</option>
	<option id="31936" name="helios_opt">
		<!-- MP Recovery Rate + 2 -->
	</option>
	<option id="31937" name="helios_opt">
		<!-- MP Recovery Rate + 3 -->
	</option>
	<option id="31938" name="helios_opt">
		<!-- CP Recovery Rate + 1 -->
	</option>
	<option id="31939" name="helios_opt">
		<!-- CP Recovery Rate + 2 -->
	</option>
	<option id="31940" name="helios_opt">
		<!-- CP Recovery Rate + 3 -->
	</option>
	<option id="31941" name="helios_opt">
		<!-- CP Recovery Rate + 5 -->
	</option>
	<option id="31942" name="helios_opt">
		<!-- Fire Resistance + 3 -->
	</option>
	<option id="31943" name="helios_opt">
		<!-- Fire Resistance + 4 -->
	</option>
	<option id="31944" name="helios_opt">
		<!-- Fire Resistance + 5 -->
	</option>
	<option id="31945" name="helios_opt">
		<!-- Fire Resistance + 10 -->
	</option>
	<option id="31946" name="helios_opt">
		<!-- Water Resistance + 3 -->
	</option>
	<option id="31947" name="helios_opt">
		<!-- Water Resistance + 4 -->
	</option>
	<option id="31948" name="helios_opt">
		<!-- Water Resistance + 5 -->
	</option>
	<option id="31949" name="helios_opt">
		<!-- Water Resistance + 10 -->
	</option>
	<option id="31950" name="helios_opt">
		<!-- Wind Resistance + 3 -->
	</option>
	<option id="31951" name="helios_opt">
		<!-- Wind Resistance + 4 -->
	</option>
	<option id="31952" name="helios_opt">
		<!-- Wind Resistance + 5 -->
	</option>
	<option id="31953" name="helios_opt">
		<!-- Wind Resistance + 10 -->
	</option>
	<option id="31954" name="helios_opt">
		<!-- Earth Resistance + 3 -->
	</option>
	<option id="31955" name="helios_opt">
		<!-- Earth Resistance + 4 -->
	</option>
	<option id="31956" name="helios_opt">
		<!-- Earth Resistance + 5 -->
	</option>
	<option id="31957" name="helios_opt">
		<!-- Earth Resistance + 10 -->
	</option>
	<option id="31958" name="helios_opt">
		<!-- Holy Resistance + 3 -->
	</option>
	<option id="31959" name="helios_opt">
		<!-- Holy Resistance + 4 -->
	</option>
	<option id="31960" name="helios_opt">
		<!-- Holy Resistance + 5 -->
	</option>
	<option id="31961" name="helios_opt">
		<!-- Holy Resistance + 10 -->
	</option>
	<option id="31962" name="helios_opt">
		<!-- Dark Resistance + 3 -->
	</option>
	<option id="31963" name="helios_opt">
		<!-- Dark Resistance + 4 -->
	</option>
	<option id="31964" name="helios_opt">
		<!-- Dark Resistance + 5 -->
	</option>
	<option id="31965" name="helios_opt">
		<!-- Dark Resistance + 10 -->
	</option>
	<option id="31966" name="helios_opt">
		<!-- Stun Resistance + 2% -->
	</option>
	<option id="31967" name="helios_opt">
		<!-- Stun Resistance + 3% -->
	</option>
	<option id="31968" name="helios_opt">
		<!-- Stun Resistance + 5% -->
	</option>
	<option id="31969" name="helios_opt">
		<!-- Hold Resistance + 2% -->
	</option>
	<option id="31970" name="helios_opt">
		<!-- Hold Resistance + 3% -->
	</option>
	<option id="31971" name="helios_opt">
		<!-- Hold Resistance + 5% -->
	</option>
	<option id="31972" name="helios_opt">
		<!-- Bleed Resistance + 2% -->
	</option>
	<option id="31973" name="helios_opt">
		<!-- Bleed Resistance + 3% -->
	</option>
	<option id="31974" name="helios_opt">
		<!-- Bleed Resistance + 5% -->
	</option>
	<option id="31975" name="helios_opt">
		<!-- Paralysis Resistance + 2% -->
	</option>
	<option id="31976" name="helios_opt">
		<!-- Paralysis Resistance + 3% -->
	</option>
	<option id="31977" name="helios_opt">
		<!-- Paralysis Resistance + 5% -->
	</option>
	<option id="31978" name="helios_opt">
		<!-- Mental Resistance + 2% -->
	</option>
	<option id="31979" name="helios_opt">
		<!-- Mental Resistance + 3% -->
	</option>
	<option id="31980" name="helios_opt">
		<!-- Mental Resistance + 5% -->
	</option>
	<option id="31981" name="helios_opt">
		<!-- Sleep Resistance + 2% -->
	</option>
	<option id="31982" name="helios_opt">
		<!-- Sleep Resistance + 3% -->
	</option>
	<option id="31983" name="helios_opt">
		<!-- Sleep Resistance + 5% -->
	</option>
	<option id="31984" name="helios_opt">
		<!-- Poison Resistance + 2% -->
	</option>
	<option id="31985" name="helios_opt">
		<!-- Poison Resistance + 3% -->
	</option>
	<option id="31986" name="helios_opt">
		<!-- Poison Resistance + 5% -->
	</option>
	<option id="31987" name="helios_opt">
		<!-- Knock Back/Knock Down Resistance + 2% -->
	</option>
	<option id="31988" name="helios_opt">
		<!-- Knock Back/Knock Down Resistance + 3% -->
	</option>
	<option id="31989" name="helios_opt">
		<!-- Knock Back/Knock Down Resistance + 5% -->
	</option>
	<option id="31990" name="helios_opt">
		<!-- Aerial Yoke Resistance + 2% -->
	</option>
	<option id="31991" name="helios_opt">
		<!-- Aerial Yoke Resistance + 3% -->
	</option>
	<option id="31992" name="helios_opt">
		<!-- Aerial Yoke Resistance + 5% -->
	</option>
	<option id="31993" name="helios_opt">
		<!-- Pull Resistance + 2% -->
	</option>
	<option id="31994" name="helios_opt">
		<!-- Pull Resistance + 3% -->
	</option>
	<option id="31995" name="helios_opt">
		<!-- Pull Resistance + 5% -->
	</option>
	<option id="31996" name="helios_opt">
		<!-- Passive: Petrification Resistance + 2%. -->
		<passive_skill id="13765" level="7" />
	</option>
	<option id="31997" name="helios_opt">
		<!-- Passive: Petrification Resistance + 3%. -->
		<passive_skill id="13765" level="8" />
	</option>
	<option id="31998" name="helios_opt">
		<!-- Passive: Petrification Resistance + 4%. -->
		<passive_skill id="13765" level="9" />
	</option>
	<option id="31999" name="helios_opt">
		<!-- Stun/Hold Resistance + 6% -->
	</option>
</list>
